algebraic_immunity_utils-1.6.0.dist-info/METADATA
algebraic_immunity_utils-1.6.0.dist-info/WHEEL
algebraic_immunity_utils/__init__.py
algebraic_immunity_utils/algebraic_immunity_utils.cp313-win_amd64.pyd
algebraic_immunity_utils-1.6.0.dist-info/RECORD
