Metadata-Version: 2.4
Name: algebraic_immunity_utils
Version: 1.6.0
Classifier: Programming Language :: Rust
Classifier: Programming Language :: Python :: Implementation :: CPython
Classifier: Programming Language :: Python :: Implementation :: PyPy
Summary: A Rust-based Python package
Home-Page: https://github.com/LucaBonamino/algebraic_immunity_utils
Author: LucaBonamino
License: MIT
Requires-Python: >=3.6
Project-URL: Homepage, https://github.com/LucaBonamino/algebraic_immunity_utils
Project-URL: Repository, https://github.com/LucaBonamino/algebraic_immunity_utils
